{
    "name": "gcp-plane",
    "nodes": [
        {
            "id": 0,
            "out": [
                1
            ],
            "x": 50,
            "y": 340
        },
        {
            "id": 1,
            "out": [
                2
            ],
            "x": 50,
            "y": 300
        },
        {
            "id": 2,
            "out": [
                3
            ],
            "x": 50,
            "y": 260
        },
        {
            "id": 3,
            "out": [
                4
            ],
            "x": 50,
            "y": 220
        },
        {
            "id": 4,
            "out": [
                5
            ],
            "x": 50,
            "y": 180
        },
        {
            "id": 5,
            "out": [
                6
            ],
            "x": 90,
            "y": 180
        },
        {
            "id": 6,
            "out": [
                7
            ],
            "x": 130,
            "y": 180
        },
        {
            "id": 7,
            "out": [
                8,
                10,
                11
            ],
            "x": 170,
            "y": 180
        },
        {
            "id": 8,
            "out": [
                13,
                14
            ],
            "x": 210,
            "y": 180
        },
        {
            "id": 9,
            "out": [],
            "x": 250,
            "y": 180
        },
        {
            "id": 10,
            "out": [
                9
            ],
            "x": 290,
            "y": 180
        },
        {
            "id": 11,
            "out": [],
            "x": 330,
            "y": 180
        },
        {
            "id": 12,
            "out": [],
            "x": 370,
            "y": 180
        },
        {
            "id": 13,
            "out": [
                12
            ],
            "x": 410,
            "y": 180
        },
        {
            "id": 14,
            "out": [],
            "x": 450,
            "y": 180
        },
        {
            "id": 15,
            "out": [],
            "x": 490,
            "y": 180
        },
        {
            "id": 16,
            "out": [],
            "x": 530,
            "y": 180
        },
        {
            "id": 17,
            "out": [],
            "x": 570,
            "y": 180
        },
        {
            "id": 18,
            "out": [],
            "x": 610,
            "y": 180
        },
        {
            "id": 19,
            "out": [],
            "x": 650,
            "y": 180
        },
        {
            "id": 20,
            "out": [],
            "x": 690,
            "y": 180
        },
        {
            "id": 21,
            "out": [],
            "x": 730,
            "y": 180
        },
        {
            "id": 22,
            "out": [],
            "x": 770,
            "y": 180
        },
        {
            "id": 23,
            "out": [],
            "x": 90,
            "y": 260,
            "seat": {
                "aisle": 1,
                "number": "A",
                "class": "first",
                "direction": "W"
            }
        },
        {
            "id": 24,
            "out": [],
            "x": 90,
            "y": 220,
            "seat": {
                "aisle": 1,
                "number": "B",
                "class": "first",
                "direction": "W"
            }
        },
        {
            "id": 25,
            "out": [],
            "x": 90,
            "y": 140,
            "seat": {
                "aisle": 1,
                "number": "C",
                "class": "first",
                "direction": "W"
            }
        },
        {
            "id": 26,
            "out": [],
            "x": 90,
            "y": 100,
            "seat": {
                "aisle": 1,
                "number": "D",
                "class": "first",
                "direction": "W"
            }
        },
        {
            "id": 27,
            "out": [],
            "x": 130,
            "y": 260,
            "seat": {
                "aisle": 2,
                "number": "A",
                "class": "first",
                "direction": "W"
            }
        },
        {
            "id": 28,
            "out": [],
            "x": 130,
            "y": 220,
            "seat": {
                "aisle": 2,
                "number": "B",
                "class": "first",
                "direction": "W"
            }
        },
        {
            "id": 29,
            "out": [],
            "x": 130,
            "y": 140,
            "seat": {
                "aisle": 2,
                "number": "C",
                "class": "first",
                "direction": "W"
            }
        },
        {
            "id": 30,
            "out": [],
            "x": 130,
            "y": 100,
            "seat": {
                "aisle": 2,
                "number": "D",
                "class": "first",
                "direction": "W"
            }
        },
        {
            "id": 31,
            "out": [],
            "x": 170,
            "y": 300,
            "seat": {
                "aisle": 3,
                "number": "A",
                "class": "coach",
                "direction": "W"
            }
        },
        {
            "id": 32,
            "out": [],
            "x": 170,
            "y": 260,
            "seat": {
                "aisle": 3,
                "number": "B",
                "class": "coach",
                "direction": "W"
            }
        },
        {
            "id": 33,
            "out": [],
            "x": 170,
            "y": 220,
            "seat": {
                "aisle": 3,
                "number": "C",
                "class": "coach",
                "direction": "W"
            }
        },
        {
            "id": 34,
            "out": [],
            "x": 170,
            "y": 140,
            "seat": {
                "aisle": 3,
                "number": "D",
                "class": "coach",
                "direction": "W"
            }
        },
        {
            "id": 35,
            "out": [],
            "x": 170,
            "y": 100,
            "seat": {
                "aisle": 3,
                "number": "E",
                "class": "coach",
                "direction": "W"
            }
        },
        {
            "id": 36,
            "out": [],
            "x": 170,
            "y": 60,
            "seat": {
                "aisle": 3,
                "number": "R",
                "class": "coach",
                "direction": "W"
            }
        },
        {
            "id": 37,
            "out": [],
            "x": 210,
            "y": 300,
            "seat": {
                "aisle": 4,
                "number": "A",
                "class": "coach",
                "direction": "W"
            }
        },
        {
            "id": 38,
            "out": [],
            "x": 210,
            "y": 260,
            "seat": {
                "aisle": 4,
                "number": "B",
                "class": "coach",
                "direction": "W"
            }
        },
        {
            "id": 39,
            "out": [],
            "x": 210,
            "y": 220,
            "seat": {
                "aisle": 4,
                "number": "C",
                "class": "coach",
                "direction": "W"
            }
        },
        {
            "id": 40,
            "out": [],
            "x": 210,
            "y": 140,
            "seat": {
                "aisle": 4,
                "number": "D",
                "class": "coach",
                "direction": "W"
            }
        },
        {
            "id": 41,
            "out": [],
            "x": 210,
            "y": 100,
            "seat": {
                "aisle": 4,
                "number": "E",
                "class": "coach",
                "direction": "W"
            }
        },
        {
            "id": 42,
            "out": [],
            "x": 210,
            "y": 60,
            "seat": {
                "aisle": 4,
                "number": "F",
                "class": "coach",
                "direction": "W"
            }
        },
        {
            "id": 43,
            "out": [],
            "x": 250,
            "y": 300,
            "seat": {
                "aisle": 5,
                "number": "A",
                "class": "coach",
                "direction": "W"
            }
        },
        {
            "id": 44,
            "out": [],
            "x": 250,
            "y": 260,
            "seat": {
                "aisle": 5,
                "number": "B",
                "class": "coach",
                "direction": "W"
            }
        },
        {
            "id": 45,
            "out": [],
            "x": 250,
            "y": 220,
            "seat": {
                "aisle": 5,
                "number": "C",
                "class": "coach",
                "direction": "W"
            }
        },
        {
            "id": 46,
            "out": [],
            "x": 250,
            "y": 140,
            "seat": {
                "aisle": 5,
                "number": "D",
                "class": "coach",
                "direction": "W"
            }
        },
        {
            "id": 47,
            "out": [],
            "x": 250,
            "y": 100,
            "seat": {
                "aisle": 5,
                "number": "E",
                "class": "coach",
                "direction": "W"
            }
        },
        {
            "id": 48,
            "out": [],
            "x": 250,
            "y": 60,
            "seat": {
                "aisle": 5,
                "number": "F",
                "class": "coach",
                "direction": "W"
            }
        },
        {
            "id": 49,
            "out": [],
            "x": 290,
            "y": 300,
            "seat": {
                "aisle": 6,
                "number": "A",
                "class": "coach",
                "direction": "W"
            }
        },
        {
            "id": 50,
            "out": [],
            "x": 290,
            "y": 260,
            "seat": {
                "aisle": 6,
                "number": "B",
                "class": "coach",
                "direction": "W"
            }
        },
        {
            "id": 51,
            "out": [],
            "x": 290,
            "y": 220,
            "seat": {
                "aisle": 6,
                "number": "C",
                "class": "coach",
                "direction": "W"
            }
        },
        {
            "id": 52,
            "out": [],
            "x": 290,
            "y": 140,
            "seat": {
                "aisle": 6,
                "number": "D",
                "class": "coach",
                "direction": "W"
            }
        },
        {
            "id": 53,
            "out": [],
            "x": 290,
            "y": 100,
            "seat": {
                "aisle": 6,
                "number": "E",
                "class": "coach",
                "direction": "W"
            }
        },
        {
            "id": 54,
            "out": [],
            "x": 290,
            "y": 60,
            "seat": {
                "aisle": 6,
                "number": "F",
                "class": "coach",
                "direction": "W"
            }
        },
        {
            "id": 55,
            "out": [],
            "x": 330,
            "y": 300,
            "seat": {
                "aisle": 7,
                "number": "A",
                "class": "coach",
                "direction": "W"
            }
        },
        {
            "id": 56,
            "out": [],
            "x": 330,
            "y": 260,
            "seat": {
                "aisle": 7,
                "number": "B",
                "class": "coach",
                "direction": "W"
            }
        },
        {
            "id": 57,
            "out": [],
            "x": 330,
            "y": 220,
            "seat": {
                "aisle": 7,
                "number": "C",
                "class": "coach",
                "direction": "W"
            }
        },
        {
            "id": 58,
            "out": [],
            "x": 330,
            "y": 140,
            "seat": {
                "aisle": 7,
                "number": "D",
                "class": "coach",
                "direction": "W"
            }
        },
        {
            "id": 59,
            "out": [],
            "x": 330,
            "y": 100,
            "seat": {
                "aisle": 7,
                "number": "E",
                "class": "coach",
                "direction": "W"
            }
        },
        {
            "id": 60,
            "out": [],
            "x": 330,
            "y": 60,
            "seat": {
                "aisle": 7,
                "number": "F",
                "class": "coach",
                "direction": "W"
            }
        },
        {
            "id": 61,
            "out": [],
            "x": 370,
            "y": 300,
            "seat": {
                "aisle": 8,
                "number": "A",
                "class": "coach",
                "direction": "W"
            }
        },
        {
            "id": 62,
            "out": [],
            "x": 370,
            "y": 260,
            "seat": {
                "aisle": 8,
                "number": "B",
                "class": "coach",
                "direction": "W"
            }
        },
        {
            "id": 63,
            "out": [],
            "x": 370,
            "y": 220,
            "seat": {
                "aisle": 8,
                "number": "C",
                "class": "coach",
                "direction": "W"
            }
        },
        {
            "id": 64,
            "out": [],
            "x": 370,
            "y": 140,
            "seat": {
                "aisle": 8,
                "number": "D",
                "class": "coach",
                "direction": "W"
            }
        },
        {
            "id": 65,
            "out": [],
            "x": 370,
            "y": 100,
            "seat": {
                "aisle": 8,
                "number": "E",
                "class": "coach",
                "direction": "W"
            }
        },
        {
            "id": 66,
            "out": [],
            "x": 370,
            "y": 60,
            "seat": {
                "aisle": 8,
                "number": "F",
                "class": "coach",
                "direction": "W"
            }
        },
        {
            "id": 67,
            "out": [],
            "x": 410,
            "y": 300,
            "seat": {
                "aisle": 9,
                "number": "A",
                "class": "coach",
                "direction": "W"
            }
        },
        {
            "id": 68,
            "out": [],
            "x": 410,
            "y": 260,
            "seat": {
                "aisle": 9,
                "number": "B",
                "class": "coach",
                "direction": "W"
            }
        },
        {
            "id": 69,
            "out": [],
            "x": 410,
            "y": 220,
            "seat": {
                "aisle": 9,
                "number": "C",
                "class": "coach",
                "direction": "W"
            }
        },
        {
            "id": 70,
            "out": [],
            "x": 410,
            "y": 140,
            "seat": {
                "aisle": 9,
                "number": "D",
                "class": "coach",
                "direction": "W"
            }
        },
        {
            "id": 71,
            "out": [],
            "x": 410,
            "y": 100,
            "seat": {
                "aisle": 9,
                "number": "E",
                "class": "coach",
                "direction": "W"
            }
        },
        {
            "id": 72,
            "out": [],
            "x": 410,
            "y": 60,
            "seat": {
                "aisle": 9,
                "number": "F",
                "class": "coach",
                "direction": "W"
            }
        },
        {
            "id": 73,
            "out": [],
            "x": 450,
            "y": 300,
            "seat": {
                "aisle": 10,
                "number": "A",
                "class": "coach",
                "direction": "W"
            }
        },
        {
            "id": 74,
            "out": [],
            "x": 450,
            "y": 260,
            "seat": {
                "aisle": 10,
                "number": "B",
                "class": "coach",
                "direction": "W"
            }
        },
        {
            "id": 75,
            "out": [],
            "x": 450,
            "y": 220,
            "seat": {
                "aisle": 10,
                "number": "C",
                "class": "coach",
                "direction": "W"
            }
        },
        {
            "id": 76,
            "out": [],
            "x": 450,
            "y": 140,
            "seat": {
                "aisle": 10,
                "number": "D",
                "class": "coach",
                "direction": "W"
            }
        },
        {
            "id": 77,
            "out": [],
            "x": 450,
            "y": 100,
            "seat": {
                "aisle": 10,
                "number": "E",
                "class": "coach",
                "direction": "W"
            }
        },
        {
            "id": 78,
            "out": [],
            "x": 450,
            "y": 60,
            "seat": {
                "aisle": 10,
                "number": "F",
                "class": "coach",
                "direction": "W"
            }
        },
        {
            "id": 79,
            "out": [],
            "x": 490,
            "y": 300,
            "seat": {
                "aisle": 11,
                "number": "A",
                "class": "coach",
                "direction": "W"
            }
        },
        {
            "id": 80,
            "out": [],
            "x": 490,
            "y": 260,
            "seat": {
                "aisle": 11,
                "number": "B",
                "class": "coach",
                "direction": "W"
            }
        },
        {
            "id": 81,
            "out": [],
            "x": 490,
            "y": 220,
            "seat": {
                "aisle": 11,
                "number": "C",
                "class": "coach",
                "direction": "W"
            }
        },
        {
            "id": 82,
            "out": [],
            "x": 490,
            "y": 140,
            "seat": {
                "aisle": 11,
                "number": "D",
                "class": "coach",
                "direction": "W"
            }
        },
        {
            "id": 83,
            "out": [],
            "x": 490,
            "y": 100,
            "seat": {
                "aisle": 11,
                "number": "E",
                "class": "coach",
                "direction": "W"
            }
        },
        {
            "id": 84,
            "out": [],
            "x": 490,
            "y": 60,
            "seat": {
                "aisle": 11,
                "number": "F",
                "class": "coach",
                "direction": "W"
            }
        },
        {
            "id": 85,
            "out": [],
            "x": 530,
            "y": 300,
            "seat": {
                "aisle": 12,
                "number": "A",
                "class": "coach",
                "direction": "W"
            }
        },
        {
            "id": 86,
            "out": [],
            "x": 530,
            "y": 260,
            "seat": {
                "aisle": 12,
                "number": "B",
                "class": "coach",
                "direction": "W"
            }
        },
        {
            "id": 87,
            "out": [],
            "x": 530,
            "y": 220,
            "seat": {
                "aisle": 12,
                "number": "C",
                "class": "coach",
                "direction": "W"
            }
        },
        {
            "id": 88,
            "out": [],
            "x": 530,
            "y": 140,
            "seat": {
                "aisle": 12,
                "number": "D",
                "class": "coach",
                "direction": "W"
            }
        },
        {
            "id": 89,
            "out": [],
            "x": 530,
            "y": 100,
            "seat": {
                "aisle": 12,
                "number": "E",
                "class": "coach",
                "direction": "W"
            }
        },
        {
            "id": 90,
            "out": [],
            "x": 530,
            "y": 60,
            "seat": {
                "aisle": 12,
                "number": "F",
                "class": "coach",
                "direction": "W"
            }
        },
        {
            "id": 91,
            "out": [],
            "x": 570,
            "y": 300,
            "seat": {
                "aisle": 13,
                "number": "A",
                "class": "coach",
                "direction": "W"
            }
        },
        {
            "id": 92,
            "out": [],
            "x": 570,
            "y": 260,
            "seat": {
                "aisle": 13,
                "number": "B",
                "class": "coach",
                "direction": "W"
            }
        },
        {
            "id": 93,
            "out": [],
            "x": 570,
            "y": 220,
            "seat": {
                "aisle": 13,
                "number": "C",
                "class": "coach",
                "direction": "W"
            }
        },
        {
            "id": 94,
            "out": [],
            "x": 570,
            "y": 140,
            "seat": {
                "aisle": 13,
                "number": "D",
                "class": "coach",
                "direction": "W"
            }
        },
        {
            "id": 95,
            "out": [],
            "x": 570,
            "y": 100,
            "seat": {
                "aisle": 13,
                "number": "E",
                "class": "coach",
                "direction": "W"
            }
        },
        {
            "id": 96,
            "out": [],
            "x": 570,
            "y": 60,
            "seat": {
                "aisle": 13,
                "number": "F",
                "class": "coach",
                "direction": "W"
            }
        },
        {
            "id": 97,
            "out": [],
            "x": 610,
            "y": 300,
            "seat": {
                "aisle": 14,
                "number": "A",
                "class": "coach",
                "direction": "W"
            }
        },
        {
            "id": 98,
            "out": [],
            "x": 610,
            "y": 260,
            "seat": {
                "aisle": 14,
                "number": "B",
                "class": "coach",
                "direction": "W"
            }
        },
        {
            "id": 99,
            "out": [],
            "x": 610,
            "y": 220,
            "seat": {
                "aisle": 14,
                "number": "C",
                "class": "coach",
                "direction": "W"
            }
        },
        {
            "id": 100,
            "out": [],
            "x": 610,
            "y": 140,
            "seat": {
                "aisle": 14,
                "number": "D",
                "class": "coach",
                "direction": "W"
            }
        },
        {
            "id": 101,
            "out": [],
            "x": 610,
            "y": 100,
            "seat": {
                "aisle": 14,
                "number": "E",
                "class": "coach",
                "direction": "W"
            }
        },
        {
            "id": 102,
            "out": [],
            "x": 610,
            "y": 60,
            "seat": {
                "aisle": 14,
                "number": "F",
                "class": "coach",
                "direction": "W"
            }
        },
        {
            "id": 103,
            "out": [],
            "x": 650,
            "y": 300,
            "seat": {
                "aisle": 15,
                "number": "A",
                "class": "coach",
                "direction": "W"
            }
        },
        {
            "id": 104,
            "out": [],
            "x": 650,
            "y": 260,
            "seat": {
                "aisle": 15,
                "number": "B",
                "class": "coach",
                "direction": "W"
            }
        },
        {
            "id": 105,
            "out": [],
            "x": 650,
            "y": 220,
            "seat": {
                "aisle": 15,
                "number": "C",
                "class": "coach",
                "direction": "W"
            }
        },
        {
            "id": 106,
            "out": [],
            "x": 650,
            "y": 140,
            "seat": {
                "aisle": 15,
                "number": "D",
                "class": "coach",
                "direction": "W"
            }
        },
        {
            "id": 107,
            "out": [],
            "x": 650,
            "y": 100,
            "seat": {
                "aisle": 15,
                "number": "E",
                "class": "coach",
                "direction": "W"
            }
        },
        {
            "id": 108,
            "out": [],
            "x": 650,
            "y": 60,
            "seat": {
                "aisle": 15,
                "number": "F",
                "class": "coach",
                "direction": "W"
            }
        },
        {
            "id": 109,
            "out": [],
            "x": 690,
            "y": 300,
            "seat": {
                "aisle": 16,
                "number": "A",
                "class": "coach",
                "direction": "W"
            }
        },
        {
            "id": 110,
            "out": [],
            "x": 690,
            "y": 260,
            "seat": {
                "aisle": 16,
                "number": "B",
                "class": "coach",
                "direction": "W"
            }
        },
        {
            "id": 111,
            "out": [],
            "x": 690,
            "y": 220,
            "seat": {
                "aisle": 16,
                "number": "C",
                "class": "coach",
                "direction": "W"
            }
        },
        {
            "id": 112,
            "out": [],
            "x": 690,
            "y": 140,
            "seat": {
                "aisle": 16,
                "number": "D",
                "class": "coach",
                "direction": "W"
            }
        },
        {
            "id": 113,
            "out": [],
            "x": 690,
            "y": 100,
            "seat": {
                "aisle": 16,
                "number": "E",
                "class": "coach",
                "direction": "W"
            }
        },
        {
            "id": 114,
            "out": [],
            "x": 690,
            "y": 60,
            "seat": {
                "aisle": 16,
                "number": "F",
                "class": "coach",
                "direction": "W"
            }
        },
        {
            "id": 115,
            "out": [],
            "x": 730,
            "y": 300,
            "seat": {
                "aisle": 17,
                "number": "A",
                "class": "coach",
                "direction": "W"
            }
        },
        {
            "id": 116,
            "out": [],
            "x": 730,
            "y": 260,
            "seat": {
                "aisle": 17,
                "number": "B",
                "class": "coach",
                "direction": "W"
            }
        },
        {
            "id": 117,
            "out": [],
            "x": 730,
            "y": 220,
            "seat": {
                "aisle": 17,
                "number": "C",
                "class": "coach",
                "direction": "W"
            }
        },
        {
            "id": 118,
            "out": [],
            "x": 730,
            "y": 140,
            "seat": {
                "aisle": 17,
                "number": "D",
                "class": "coach",
                "direction": "W"
            }
        },
        {
            "id": 119,
            "out": [],
            "x": 730,
            "y": 100,
            "seat": {
                "aisle": 17,
                "number": "E",
                "class": "coach",
                "direction": "W"
            }
        },
        {
            "id": 120,
            "out": [],
            "x": 730,
            "y": 60,
            "seat": {
                "aisle": 17,
                "number": "F",
                "class": "coach",
                "direction": "W"
            }
        },
        {
            "id": 121,
            "out": [],
            "x": 770,
            "y": 300,
            "seat": {
                "aisle": 18,
                "number": "A",
                "class": "coach",
                "direction": "W"
            }
        },
        {
            "id": 122,
            "out": [],
            "x": 770,
            "y": 260,
            "seat": {
                "aisle": 18,
                "number": "B",
                "class": "coach",
                "direction": "W"
            }
        },
        {
            "id": 123,
            "out": [],
            "x": 770,
            "y": 220,
            "seat": {
                "aisle": 18,
                "number": "C",
                "class": "coach",
                "direction": "W"
            }
        },
        {
            "id": 124,
            "out": [],
            "x": 770,
            "y": 140,
            "seat": {
                "aisle": 18,
                "number": "D",
                "class": "coach",
                "direction": "W"
            }
        },
        {
            "id": 125,
            "out": [],
            "x": 770,
            "y": 100,
            "seat": {
                "aisle": 18,
                "number": "E",
                "class": "coach",
                "direction": "W"
            }
        },
        {
            "id": 126,
            "out": [],
            "x": 770,
            "y": 60,
            "seat": {
                "aisle": 18,
                "number": "F",
                "class": "coach",
                "direction": "W"
            }
        }
    ],
    "passengers": [
        {
            "id": 0,
            "node": 0,
            "direction": "N",
            "baggage": [
                {
                    "size": 3
                }
            ],
            "ticket": {
                "class": "coach",
                "aisle": 1,
                "number": "B",
                "direction": "W"
            }
        }
    ]
}